setup.py
odoo/addons/helpdesk_ticket_board_logistics/CHANGELOG.md
odoo/addons/helpdesk_ticket_board_logistics/README.rst
odoo/addons/helpdesk_ticket_board_logistics/__init__.py
odoo/addons/helpdesk_ticket_board_logistics/__manifest__.py
odoo/addons/helpdesk_ticket_board_logistics/hooks.py
odoo/addons/helpdesk_ticket_board_logistics/data/helpdesk_ticket_team.xml
odoo/addons/helpdesk_ticket_board_logistics/i18n/ca_ES.po
odoo/addons/helpdesk_ticket_board_logistics/i18n/es.po
odoo/addons/helpdesk_ticket_board_logistics/models/__init__.py
odoo/addons/helpdesk_ticket_board_logistics/models/helpdesk_ticket.py
odoo/addons/helpdesk_ticket_board_logistics/models/helpdesk_ticket_team.py
odoo/addons/helpdesk_ticket_board_logistics/static/description/icon.png
odoo/addons/helpdesk_ticket_board_logistics/tests/__init__.py
odoo/addons/helpdesk_ticket_board_logistics/tests/test_helpdesk_ticket.py
odoo/addons/helpdesk_ticket_board_logistics/views/helpdesk_dashboard_view.xml
odoo/addons/helpdesk_ticket_board_logistics/views/helpdesk_ticket_view.xml
odoo_addon_helpdesk_ticket_board_logistics.egg-info/PKG-INFO
odoo_addon_helpdesk_ticket_board_logistics.egg-info/SOURCES.txt
odoo_addon_helpdesk_ticket_board_logistics.egg-info/dependency_links.txt
odoo_addon_helpdesk_ticket_board_logistics.egg-info/not-zip-safe
odoo_addon_helpdesk_ticket_board_logistics.egg-info/requires.txt
odoo_addon_helpdesk_ticket_board_logistics.egg-info/top_level.txt